search_api/__init__.py
search_api/client.py
view_api/__init__.py
view_api/client.py
ytnidongde-0.1.0.dist-info/METADATA
ytnidongde-0.1.0.dist-info/WHEEL
ytnidongde-0.1.0.dist-info/top_level.txt
ytnidongde-0.1.0.dist-info/RECORD
