Metadata-Version: 2.4
Name: YTnidongde
Version: 0.1.0
Summary: Video search API package
Home-page: https://github.com/928368902/YTnidongde
Author: 天球生物
Author-email: xuanatwm@gmail.com
Requires-Dist: requests
Dynamic: author
Dynamic: author-email
Dynamic: home-page
Dynamic: requires-dist
Dynamic: summary
